younger/__init__.py
younger/applications/__init__.py
younger/applications/deep_learning.py
younger/applications/datasets/__init__.py
younger/applications/datasets/architecture_dataset.py
younger/applications/datasets/block_dataset.py
younger/applications/datasets/ego_dataset.py
younger/applications/datasets/link_dataset.py
younger/applications/datasets/node_dataset.py
younger/applications/datasets/ssl_dataset.py
younger/applications/models/__init__.py
younger/applications/models/glass.py
younger/applications/models/napp_gat_base.py
younger/applications/models/napp_gat_vary_v1.py
younger/applications/models/napp_gin_base.py
younger/applications/models/embedding/__init__.py
younger/applications/models/embedding/mae_gin.py
younger/applications/models/link_prediction/__init__.py
younger/applications/models/link_prediction/gat_lp.py
younger/applications/models/link_prediction/gcn_lp.py
younger/applications/models/link_prediction/sage_lp.py
younger/applications/models/link_prediction/vgae_lp.py
younger/applications/models/node_prediction/__init__.py
younger/applications/models/node_prediction/ae_np.py
younger/applications/models/node_prediction/gat_np.py
younger/applications/models/node_prediction/gcn_np.py
younger/applications/models/node_prediction/gin_np.py
younger/applications/models/node_prediction/sage_np.py
younger/applications/tasks/__init__.py
younger/applications/tasks/base_task.py
younger/applications/tasks/block_embedding.py
younger/applications/tasks/graph_embedding.py
younger/applications/tasks/link_prediction.py
younger/applications/tasks/node_embedding.py
younger/applications/tasks/node_prediction.py
younger/applications/tasks/performance_prediction.py
younger/applications/tasks/ssl_prediction.py
younger/applications/tasks/subgraph_embedding.py
younger/applications/utils/neural_network.py
younger/benchmarks/__init__.py
younger/benchmarks/analyze.py
younger/benchmarks/generate.py
younger/benchmarks/merge.py
younger/benchmarks/prepare.py
Younger-0.0.1a2.dist-info/LICENSE
Younger-0.0.1a2.dist-info/METADATA
Younger-0.0.1a2.dist-info/WHEEL
Younger-0.0.1a2.dist-info/entry_points.txt
Younger-0.0.1a2.dist-info/top_level.txt
Younger-0.0.1a2.dist-info/RECORD
